CHANGES.txt
MANIFEST.in
README.rst
setup.py
FileDistribution.egg-info/PKG-INFO
FileDistribution.egg-info/SOURCES.txt
FileDistribution.egg-info/dependency_links.txt
FileDistribution.egg-info/top_level.txt
docs/README.txt
filedistribution/__init__.py
filedistribution/file_distribution.py
filedistribution/test/__init__.py
filedistribution/test/test_file_distribution.py