Metadata-Version: 1.1
Name: FileDistribution
Version: 0.1.1
Summary: Simple file distribution library.
Home-page: http://github.org/caffecoder/fdist-python
Author: Adam Kubica
Author-email: caffecoder@kaizen-step.com
License: MIT
Platform: darwin
Platform: linux2
Platform: freebsd7
Classifier: Development Status :: 5 - Production/Stable
Classifier: License :: OSI Approved :: MIT License
Classifier: Programming Language :: Python :: 2.7
Classifier: Topic :: Software Development :: Libraries
